{
  "id": "2018-ncaa-mens",
  "name": "NCAA Division I Men's Basketball Tournament",
  "rounds": 7,
  "games": [
    {
      "id": "2018-ff-1",
      "tournament_id": "2018-ncaa-mens",
      "team1_id": "LIU",
      "team2_id": "Radford",
      "tipoff_time": "2018-03-13T00:00:00",
      "sort_order": 1,
      "team1_score": 61,
      "team2_score": 71,
      "next_game_id": "2018-firstround-3",
      "next_game_slot": 2,
      "is_final": true,
      "created": "2025-04-07T03:08:58.426802",
      "updated": "2025-04-07T03:08:58.426806"
    },
    {
      "id": "2018-ff-2",
      "tournament_id": "2018-ncaa-mens",
      "team1_id": "St. Bonaventure",
      "team2_id": "UCLA",
      "tipoff_time": "2018-03-13T00:00:00",
      "sort_order": 2,
      "team1_score": 65,
      "team2_score": 58,
      "next_game_id": "2018-firstround-7",
      "next_game_slot": 2,
      "is_final": true,
      "created": "2025-04-07T03:08:58.426824",
      "updated": "2025-04-07T03:08:58.426825"
    },
    {
      "id": "2018-firstround-3",
      "tournament_id": "2018-ncaa-mens",
      "team1_id": "Villanova",
      "team2_id": "Radford",
      "tipoff_time": "2018-03-15T00:00:00",
      "sort_order": 3,
      "team1_score": 87,
      "team2_score": 61,
      "next_game_id": "2018-secondround-11",
      "next_game_slot": 1,
      "is_final": true,
      "created": "2025-04-07T08:08:58.427413",
      "updated": "2025-04-07T08:08:58.427415"
    },
    {
      "id": "2018-firstround-4",
      "tournament_id": "2018-ncaa-mens",
      "team1_id": "Virginia Tech",
      "team2_id": "Alabama",
      "tipoff_time": "2018-03-15T00:00:00",
      "sort_order": 4,
      "team1_score": 83,
      "team2_score": 86,
      "next_game_id": "2018-secondround-11",
      "next_game_slot": 2,
      "is_final": true,
      "created": "2025-04-07T08:08:58.427469",
      "updated": "2025-04-07T08:08:58.427469"
    },
    {
      "id": "2018-firstround-5",
      "tournament_id": "2018-ncaa-mens",
      "team1_id": "West Virginia",
      "team2_id": "Murray State",
      "tipoff_time": "2018-03-16T00:00:00",
      "sort_order": 5,
      "team1_score": 85,
      "team2_score": 68,
      "next_game_id": "2018-secondround-12",
      "next_game_slot": 1,
      "is_final": true,
      "created": "2025-04-07T08:08:58.427518",
      "updated": "2025-04-07T08:08:58.427518"
    },
    {
      "id": "2018-firstround-6",
      "tournament_id": "2018-ncaa-mens",
      "team1_id": "Wichita State",
      "team2_id": "Marshall",
      "tipoff_time": "2018-03-16T00:00:00",
      "sort_order": 6,
      "team1_score": 75,
      "team2_score": 81,
      "next_game_id": "2018-secondround-12",
      "next_game_slot": 2,
      "is_final": true,
      "created": "2025-04-07T08:08:58.427565",
      "updated": "2025-04-07T08:08:58.427565"
    },
    {
      "id": "2018-firstround-7",
      "tournament_id": "2018-ncaa-mens",
      "team1_id": "Florida",
      "team2_id": "St. Bonaventure",
      "tipoff_time": "2018-03-15T00:00:00",
      "sort_order": 7,
      "team1_score": 77,
      "team2_score": 62,
      "next_game_id": "2018-secondround-13",
      "next_game_slot": 1,
      "is_final": true,
      "created": "2025-04-07T08:08:58.427611",
      "updated": "2025-04-07T08:08:58.427612"
    },
    {
      "id": "2018-firstround-8",
      "tournament_id": "2018-ncaa-mens",
      "team1_id": "Texas Tech",
      "team2_id": "Stephen F. Austin",
      "tipoff_time": "2018-03-15T00:00:00",
      "sort_order": 8,
      "team1_score": 70,
      "team2_score": 60,
      "next_game_id": "2018-secondround-13",
      "next_game_slot": 2,
      "is_final": true,
      "created": "2025-04-07T08:08:58.427672",
      "updated": "2025-04-07T08:08:58.427673"
    },
    {
      "id": "2018-firstround-9",
      "tournament_id": "2018-ncaa-mens",
      "team1_id": "Arkansas",
      "team2_id": "Butler",
      "tipoff_time": "2018-03-16T00:00:00",
      "sort_order": 9,
      "team1_score": 62,
      "team2_score": 79,
      "next_game_id": "2018-secondround-14",
      "next_game_slot": 1,
      "is_final": true,
      "created": "2025-04-07T08:08:58.427719",
      "updated": "2025-04-07T08:08:58.427719"
    },
    {
      "id": "2018-firstround-10",
      "tournament_id": "2018-ncaa-mens",
      "team1_id": "Purdue",
      "team2_id": "Cal State Fullerton",
      "tipoff_time": "2018-03-16T00:00:00",
      "sort_order": 10,
      "team1_score": 74,
      "team2_score": 48,
      "next_game_id": "2018-secondround-14",
      "next_game_slot": 2,
      "is_final": true,
      "created": "2025-04-07T08:08:58.427766",
      "updated": "2025-04-07T08:08:58.427767"
    },
    {
      "id": "2018-secondround-11",
      "tournament_id": "2018-ncaa-mens",
      "team1_id": "Villanova",
      "team2_id": "Alabama",
      "tipoff_time": "2018-03-17T00:00:00",
      "sort_order": 11,
      "team1_score": 81,
      "team2_score": 58,
      "next_game_id": "2018-sweet16-15",
      "next_game_slot": 1,
      "is_final": true,
      "created": "2025-04-07T08:08:58.427827",
      "updated": "2025-04-07T08:08:58.427828"
    },
    {
      "id": "2018-secondround-12",
      "tournament_id": "2018-ncaa-mens",
      "team1_id": "West Virginia",
      "team2_id": "Marshall",
      "tipoff_time": "2018-03-18T00:00:00",
      "sort_order": 12,
      "team1_score": 94,
      "team2_score": 71,
      "next_game_id": "2018-sweet16-15",
      "next_game_slot": 2,
      "is_final": true,
      "created": "2025-04-07T08:08:58.427874",
      "updated": "2025-04-07T08:08:58.427875"
    },
    {
      "id": "2018-secondround-13",
      "tournament_id": "2018-ncaa-mens",
      "team1_id": "Florida",
      "team2_id": "Texas Tech",
      "tipoff_time": "2018-03-17T00:00:00",
      "sort_order": 13,
      "team1_score": 66,
      "team2_score": 69,
      "next_game_id": "2018-sweet16-16",
      "next_game_slot": 1,
      "is_final": true,
      "created": "2025-04-07T08:08:58.427921",
      "updated": "2025-04-07T08:08:58.427922"
    },
    {
      "id": "2018-secondround-14",
      "tournament_id": "2018-ncaa-mens",
      "team1_id": "Butler",
      "team2_id": "Purdue",
      "tipoff_time": "2018-03-18T00:00:00",
      "sort_order": 14,
      "team1_score": 73,
      "team2_score": 76,
      "next_game_id": "2018-sweet16-16",
      "next_game_slot": 2,
      "is_final": true,
      "created": "2025-04-07T08:08:58.427967",
      "updated": "2025-04-07T08:08:58.427967"
    },
    {
      "id": "2018-sweet16-15",
      "tournament_id": "2018-ncaa-mens",
      "team1_id": "Villanova",
      "team2_id": "West Virginia",
      "tipoff_time": "2018-03-23T00:00:00",
      "sort_order": 15,
      "team1_score": 90,
      "team2_score": 78,
      "next_game_id": "2018-eliteeight-17",
      "next_game_slot": 1,
      "is_final": true,
      "created": "2025-04-07T08:08:58.428024",
      "updated": "2025-04-07T08:08:58.428025"
    },
    {
      "id": "2018-sweet16-16",
      "tournament_id": "2018-ncaa-mens",
      "team1_id": "Texas Tech",
      "team2_id": "Purdue",
      "tipoff_time": "2018-03-23T00:00:00",
      "sort_order": 16,
      "team1_score": 78,
      "team2_score": 65,
      "next_game_id": "2018-eliteeight-17",
      "next_game_slot": 2,
      "is_final": true,
      "created": "2025-04-07T08:08:58.428070",
      "updated": "2025-04-07T08:08:58.428071"
    },
    {
      "id": "2018-eliteeight-17",
      "tournament_id": "2018-ncaa-mens",
      "team1_id": "Villanova",
      "team2_id": "Texas Tech",
      "tipoff_time": "2018-03-25T00:00:00",
      "sort_order": 17,
      "team1_score": 71,
      "team2_score": 59,
      "next_game_id": "2018-finalfour-65",
      "next_game_slot": 1,
      "is_final": true,
      "created": "2025-04-07T08:08:58.428128",
      "updated": "2025-04-07T08:08:58.428129"
    },
    {
      "id": "2018-ff-18",
      "tournament_id": "2018-ncaa-mens",
      "team1_id": "Syracuse",
      "team2_id": "Arizona State",
      "tipoff_time": "2018-03-14T00:00:00",
      "sort_order": 18,
      "team1_score": 60,
      "team2_score": 56,
      "next_game_id": "2018-firstround-23",
      "next_game_slot": 2,
      "is_final": true,
      "created": "2025-04-07T03:08:58.428214",
      "updated": "2025-04-07T03:08:58.428216"
    },
    {
      "id": "2018-firstround-19",
      "tournament_id": "2018-ncaa-mens",
      "team1_id": "Kansas",
      "team2_id": "Penn",
      "tipoff_time": "2018-03-15T00:00:00",
      "sort_order": 19,
      "team1_score": 76,
      "team2_score": 60,
      "next_game_id": "2018-secondround-27",
      "next_game_slot": 1,
      "is_final": true,
      "created": "2025-04-07T08:08:58.428702",
      "updated": "2025-04-07T08:08:58.428703"
    },
    {
      "id": "2018-firstround-20",
      "tournament_id": "2018-ncaa-mens",
      "team1_id": "Seton Hall",
      "team2_id": "NC State",
      "tipoff_time": "2018-03-15T00:00:00",
      "sort_order": 20,
      "team1_score": 94,
      "team2_score": 83,
      "next_game_id": "2018-secondround-27",
      "next_game_slot": 2,
      "is_final": true,
      "created": "2025-04-07T08:08:58.428751",
      "updated": "2025-04-07T08:08:58.428751"
    },
    {
      "id": "2018-firstround-21",
      "tournament_id": "2018-ncaa-mens",
      "team1_id": "Clemson",
      "team2_id": "New Mexico State",
      "tipoff_time": "2018-03-16T00:00:00",
      "sort_order": 21,
      "team1_score": 79,
      "team2_score": 68,
      "next_game_id": "2018-secondround-28",
      "next_game_slot": 1,
      "is_final": true,
      "created": "2025-04-07T08:08:58.428796",
      "updated": "2025-04-07T08:08:58.428797"
    },
    {
      "id": "2018-firstround-22",
      "tournament_id": "2018-ncaa-mens",
      "team1_id": "Auburn",
      "team2_id": "College of Charleston",
      "tipoff_time": "2018-03-16T00:00:00",
      "sort_order": 22,
      "team1_score": 62,
      "team2_score": 58,
      "next_game_id": "2018-secondround-28",
      "next_game_slot": 2,
      "is_final": true,
      "created": "2025-04-07T08:08:58.428840",
      "updated": "2025-04-07T08:08:58.428841"
    },
    {
      "id": "2018-firstround-23",
      "tournament_id": "2018-ncaa-mens",
      "team1_id": "TCU",
      "team2_id": "Syracuse",
      "tipoff_time": "2018-03-16T00:00:00",
      "sort_order": 23,
      "team1_score": 52,
      "team2_score": 57,
      "next_game_id": "2018-secondround-29",
      "next_game_slot": 1,
      "is_final": true,
      "created": "2025-04-07T08:08:58.428888",
      "updated": "2025-04-07T08:08:58.428889"
    },
    {
      "id": "2018-firstround-24",
      "tournament_id": "2018-ncaa-mens",
      "team1_id": "Michigan State",
      "team2_id": "Bucknell",
      "tipoff_time": "2018-03-16T00:00:00",
      "sort_order": 24,
      "team1_score": 82,
      "team2_score": 78,
      "next_game_id": "2018-secondround-29",
      "next_game_slot": 2,
      "is_final": true,
      "created": "2025-04-07T08:08:58.428936",
      "updated": "2025-04-07T08:08:58.428937"
    },
    {
      "id": "2018-firstround-25",
      "tournament_id": "2018-ncaa-mens",
      "team1_id": "Rhode Island",
      "team2_id": "Oklahoma",
      "tipoff_time": "2018-03-15T00:00:00",
      "sort_order": 25,
      "team1_score": 83,
      "team2_score": 78,
      "next_game_id": "2018-secondround-30",
      "next_game_slot": 1,
      "is_final": true,
      "created": "2025-04-07T08:08:58.428986",
      "updated": "2025-04-07T08:08:58.428986"
    },
    {
      "id": "2018-firstround-26",
      "tournament_id": "2018-ncaa-mens",
      "team1_id": "Duke",
      "team2_id": "Iona",
      "tipoff_time": "2018-03-15T00:00:00",
      "sort_order": 26,
      "team1_score": 89,
      "team2_score": 67,
      "next_game_id": "2018-secondround-30",
      "next_game_slot": 2,
      "is_final": true,
      "created": "2025-04-07T08:08:58.429034",
      "updated": "2025-04-07T08:08:58.429037"
    },
    {
      "id": "2018-secondround-27",
      "tournament_id": "2018-ncaa-mens",
      "team1_id": "Kansas",
      "team2_id": "Seton Hall",
      "tipoff_time": "2018-03-17T00:00:00",
      "sort_order": 27,
      "team1_score": 83,
      "team2_score": 79,
      "next_game_id": "2018-sweet16-31",
      "next_game_slot": 1,
      "is_final": true,
      "created": "2025-04-07T08:08:58.429096",
      "updated": "2025-04-07T08:08:58.429097"
    },
    {
      "id": "2018-secondround-28",
      "tournament_id": "2018-ncaa-mens",
      "team1_id": "Clemson",
      "team2_id": "Auburn",
      "tipoff_time": "2018-03-18T00:00:00",
      "sort_order": 28,
      "team1_score": 84,
      "team2_score": 53,
      "next_game_id": "2018-sweet16-31",
      "next_game_slot": 2,
      "is_final": true,
      "created": "2025-04-07T08:08:58.429148",
      "updated": "2025-04-07T08:08:58.429148"
    },
    {
      "id": "2018-secondround-29",
      "tournament_id": "2018-ncaa-mens",
      "team1_id": "Syracuse",
      "team2_id": "Michigan State",
      "tipoff_time": "2018-03-18T00:00:00",
      "sort_order": 29,
      "team1_score": 55,
      "team2_score": 53,
      "next_game_id": "2018-sweet16-32",
      "next_game_slot": 1,
      "is_final": true,
      "created": "2025-04-07T08:08:58.429196",
      "updated": "2025-04-07T08:08:58.429196"
    },
    {
      "id": "2018-secondround-30",
      "tournament_id": "2018-ncaa-mens",
      "team1_id": "Rhode Island",
      "team2_id": "Duke",
      "tipoff_time": "2018-03-17T00:00:00",
      "sort_order": 30,
      "team1_score": 62,
      "team2_score": 87,
      "next_game_id": "2018-sweet16-32",
      "next_game_slot": 2,
      "is_final": true,
      "created": "2025-04-07T08:08:58.429244",
      "updated": "2025-04-07T08:08:58.429244"
    },
    {
      "id": "2018-sweet16-31",
      "tournament_id": "2018-ncaa-mens",
      "team1_id": "Kansas",
      "team2_id": "Clemson",
      "tipoff_time": "2018-03-23T00:00:00",
      "sort_order": 31,
      "team1_score": 80,
      "team2_score": 76,
      "next_game_id": "2018-eliteeight-33",
      "next_game_slot": 1,
      "is_final": true,
      "created": "2025-04-07T08:08:58.429299",
      "updated": "2025-04-07T08:08:58.429300"
    },
    {
      "id": "2018-sweet16-32",
      "tournament_id": "2018-ncaa-mens",
      "team1_id": "Syracuse",
      "team2_id": "Duke",
      "tipoff_time": "2018-03-23T00:00:00",
      "sort_order": 32,
      "team1_score": 65,
      "team2_score": 69,
      "next_game_id": "2018-eliteeight-33",
      "next_game_slot": 2,
      "is_final": true,
      "created": "2025-04-07T08:08:58.429348",
      "updated": "2025-04-07T08:08:58.429348"
    },
    {
      "id": "2018-eliteeight-33",
      "tournament_id": "2018-ncaa-mens",
      "team1_id": "Kansas",
      "team2_id": "Duke",
      "tipoff_time": "2018-03-25T00:00:00",
      "sort_order": 33,
      "team1_score": 85,
      "team2_score": 81,
      "next_game_id": "2018-finalfour-65",
      "next_game_slot": 2,
      "is_final": true,
      "created": "2025-04-07T08:08:58.429403",
      "updated": "2025-04-07T08:08:58.429404"
    },
    {
      "id": "2018-firstround-34",
      "tournament_id": "2018-ncaa-mens",
      "team1_id": "Virginia",
      "team2_id": "UMBC",
      "tipoff_time": "2018-03-16T00:00:00",
      "sort_order": 34,
      "team1_score": 54,
      "team2_score": 74,
      "next_game_id": "2018-secondround-42",
      "next_game_slot": 1,
      "is_final": true,
      "created": "2025-04-07T08:08:58.430088",
      "updated": "2025-04-07T08:08:58.430089"
    },
    {
      "id": "2018-firstround-35",
      "tournament_id": "2018-ncaa-mens",
      "team1_id": "Creighton",
      "team2_id": "Kansas State",
      "tipoff_time": "2018-03-16T00:00:00",
      "sort_order": 35,
      "team1_score": 59,
      "team2_score": 69,
      "next_game_id": "2018-secondround-42",
      "next_game_slot": 2,
      "is_final": true,
      "created": "2025-04-07T08:08:58.430136",
      "updated": "2025-04-07T08:08:58.430136"
    },
    {
      "id": "2018-firstround-36",
      "tournament_id": "2018-ncaa-mens",
      "team1_id": "Kentucky",
      "team2_id": "Davidson",
      "tipoff_time": "2018-03-15T00:00:00",
      "sort_order": 36,
      "team1_score": 78,
      "team2_score": 73,
      "next_game_id": "2018-secondround-43",
      "next_game_slot": 1,
      "is_final": true,
      "created": "2025-04-07T08:08:58.430184",
      "updated": "2025-04-07T08:08:58.430185"
    },
    {
      "id": "2018-firstround-37",
      "tournament_id": "2018-ncaa-mens",
      "team1_id": "Arizona",
      "team2_id": "Buffalo",
      "tipoff_time": "2018-03-15T00:00:00",
      "sort_order": 37,
      "team1_score": 68,
      "team2_score": 89,
      "next_game_id": "2018-secondround-43",
      "next_game_slot": 2,
      "is_final": true,
      "created": "2025-04-07T08:08:58.430232",
      "updated": "2025-04-07T08:08:58.430233"
    },
    {
      "id": "2018-firstround-38",
      "tournament_id": "2018-ncaa-mens",
      "team1_id": "Miami (FL)",
      "team2_id": "Loyola (IL)",
      "tipoff_time": "2018-03-15T00:00:00",
      "sort_order": 38,
      "team1_score": 62,
      "team2_score": 64,
      "next_game_id": "2018-secondround-44",
      "next_game_slot": 1,
      "is_final": true,
      "created": "2025-04-07T08:08:58.430276",
      "updated": "2025-04-07T08:08:58.430277"
    },
    {
      "id": "2018-firstround-39",
      "tournament_id": "2018-ncaa-mens",
      "team1_id": "Tennessee",
      "team2_id": "Wright State",
      "tipoff_time": "2018-03-15T00:00:00",
      "sort_order": 39,
      "team1_score": 73,
      "team2_score": 47,
      "next_game_id": "2018-secondround-44",
      "next_game_slot": 2,
      "is_final": true,
      "created": "2025-04-07T08:08:58.430320",
      "updated": "2025-04-07T08:08:58.430320"
    },
    {
      "id": "2018-firstround-40",
      "tournament_id": "2018-ncaa-mens",
      "team1_id": "Nevada",
      "team2_id": "Texas",
      "tipoff_time": "2018-03-16T00:00:00",
      "sort_order": 40,
      "team1_score": 87,
      "team2_score": 83,
      "next_game_id": "2018-secondround-45",
      "next_game_slot": 1,
      "is_final": true,
      "created": "2025-04-07T08:08:58.430363",
      "updated": "2025-04-07T08:08:58.430364"
    },
    {
      "id": "2018-firstround-41",
      "tournament_id": "2018-ncaa-mens",
      "team1_id": "Cincinnati",
      "team2_id": "Georgia State",
      "tipoff_time": "2018-03-16T00:00:00",
      "sort_order": 41,
      "team1_score": 68,
      "team2_score": 53,
      "next_game_id": "2018-secondround-45",
      "next_game_slot": 2,
      "is_final": true,
      "created": "2025-04-07T08:08:58.430407",
      "updated": "2025-04-07T08:08:58.430407"
    },
    {
      "id": "2018-secondround-42",
      "tournament_id": "2018-ncaa-mens",
      "team1_id": "UMBC",
      "team2_id": "Kansas State",
      "tipoff_time": "2018-03-18T00:00:00",
      "sort_order": 42,
      "team1_score": 43,
      "team2_score": 50,
      "next_game_id": "2018-sweet16-46",
      "next_game_slot": 1,
      "is_final": true,
      "created": "2025-04-07T08:08:58.430463",
      "updated": "2025-04-07T08:08:58.430463"
    },
    {
      "id": "2018-secondround-43",
      "tournament_id": "2018-ncaa-mens",
      "team1_id": "Kentucky",
      "team2_id": "Buffalo",
      "tipoff_time": "2018-03-17T00:00:00",
      "sort_order": 43,
      "team1_score": 95,
      "team2_score": 75,
      "next_game_id": "2018-sweet16-46",
      "next_game_slot": 2,
      "is_final": true,
      "created": "2025-04-07T08:08:58.430510",
      "updated": "2025-04-07T08:08:58.430510"
    },
    {
      "id": "2018-secondround-44",
      "tournament_id": "2018-ncaa-mens",
      "team1_id": "Loyola (IL)",
      "team2_id": "Tennessee",
      "tipoff_time": "2018-03-17T00:00:00",
      "sort_order": 44,
      "team1_score": 63,
      "team2_score": 62,
      "next_game_id": "2018-sweet16-47",
      "next_game_slot": 1,
      "is_final": true,
      "created": "2025-04-07T08:08:58.430555",
      "updated": "2025-04-07T08:08:58.430555"
    },
    {
      "id": "2018-secondround-45",
      "tournament_id": "2018-ncaa-mens",
      "team1_id": "Nevada",
      "team2_id": "Cincinnati",
      "tipoff_time": "2018-03-18T00:00:00",
      "sort_order": 45,
      "team1_score": 75,
      "team2_score": 73,
      "next_game_id": "2018-sweet16-47",
      "next_game_slot": 2,
      "is_final": true,
      "created": "2025-04-07T08:08:58.430597",
      "updated": "2025-04-07T08:08:58.430598"
    },
    {
      "id": "2018-sweet16-46",
      "tournament_id": "2018-ncaa-mens",
      "team1_id": "Kansas State",
      "team2_id": "Kentucky",
      "tipoff_time": "2018-03-22T00:00:00",
      "sort_order": 46,
      "team1_score": 61,
      "team2_score": 58,
      "next_game_id": "2018-eliteeight-48",
      "next_game_slot": 1,
      "is_final": true,
      "created": "2025-04-07T08:08:58.430650",
      "updated": "2025-04-07T08:08:58.430651"
    },
    {
      "id": "2018-sweet16-47",
      "tournament_id": "2018-ncaa-mens",
      "team1_id": "Loyola (IL)",
      "team2_id": "Nevada",
      "tipoff_time": "2018-03-22T00:00:00",
      "sort_order": 47,
      "team1_score": 69,
      "team2_score": 68,
      "next_game_id": "2018-eliteeight-48",
      "next_game_slot": 2,
      "is_final": true,
      "created": "2025-04-07T08:08:58.430693",
      "updated": "2025-04-07T08:08:58.430694"
    },
    {
      "id": "2018-eliteeight-48",
      "tournament_id": "2018-ncaa-mens",
      "team1_id": "Kansas State",
      "team2_id": "Loyola (IL)",
      "tipoff_time": "2018-03-24T00:00:00",
      "sort_order": 48,
      "team1_score": 62,
      "team2_score": 78,
      "next_game_id": "2018-finalfour-66",
      "next_game_slot": 1,
      "is_final": true,
      "created": "2025-04-07T08:08:58.430744",
      "updated": "2025-04-07T08:08:58.430744"
    },
    {
      "id": "2018-ff-49",
      "tournament_id": "2018-ncaa-mens",
      "team1_id": "Texas Southern",
      "team2_id": "North Carolina Central",
      "tipoff_time": "2018-03-14T00:00:00",
      "sort_order": 49,
      "team1_score": 64,
      "team2_score": 46,
      "next_game_id": "2018-firstround-50",
      "next_game_slot": 2,
      "is_final": true,
      "created": "2025-04-07T03:08:58.430866",
      "updated": "2025-04-07T03:08:58.430868"
    },
    {
      "id": "2018-firstround-50",
      "tournament_id": "2018-ncaa-mens",
      "team1_id": "Xavier",
      "team2_id": "Texas Southern",
      "tipoff_time": "2018-03-16T00:00:00",
      "sort_order": 50,
      "team1_score": 102,
      "team2_score": 83,
      "next_game_id": "2018-secondround-58",
      "next_game_slot": 1,
      "is_final": true,
      "created": "2025-04-07T08:08:58.431392",
      "updated": "2025-04-07T08:08:58.431393"
    },
    {
      "id": "2018-firstround-51",
      "tournament_id": "2018-ncaa-mens",
      "team1_id": "Missouri",
      "team2_id": "Florida State",
      "tipoff_time": "2018-03-16T00:00:00",
      "sort_order": 51,
      "team1_score": 54,
      "team2_score": 67,
      "next_game_id": "2018-secondround-58",
      "next_game_slot": 2,
      "is_final": true,
      "created": "2025-04-07T08:08:58.431446",
      "updated": "2025-04-07T08:08:58.431447"
    },
    {
      "id": "2018-firstround-52",
      "tournament_id": "2018-ncaa-mens",
      "team1_id": "Ohio State",
      "team2_id": "South Dakota State",
      "tipoff_time": "2018-03-15T00:00:00",
      "sort_order": 52,
      "team1_score": 81,
      "team2_score": 73,
      "next_game_id": "2018-secondround-59",
      "next_game_slot": 1,
      "is_final": true,
      "created": "2025-04-07T08:08:58.431495",
      "updated": "2025-04-07T08:08:58.431496"
    },
    {
      "id": "2018-firstround-53",
      "tournament_id": "2018-ncaa-mens",
      "team1_id": "Gonzaga",
      "team2_id": "UNC Greensboro",
      "tipoff_time": "2018-03-15T00:00:00",
      "sort_order": 53,
      "team1_score": 68,
      "team2_score": 64,
      "next_game_id": "2018-secondround-59",
      "next_game_slot": 2,
      "is_final": true,
      "created": "2025-04-07T08:08:58.431541",
      "updated": "2025-04-07T08:08:58.431542"
    },
    {
      "id": "2018-firstround-54",
      "tournament_id": "2018-ncaa-mens",
      "team1_id": "Houston",
      "team2_id": "San Diego State",
      "tipoff_time": "2018-03-15T00:00:00",
      "sort_order": 54,
      "team1_score": 67,
      "team2_score": 65,
      "next_game_id": "2018-secondround-60",
      "next_game_slot": 1,
      "is_final": true,
      "created": "2025-04-07T08:08:58.431588",
      "updated": "2025-04-07T08:08:58.431588"
    },
    {
      "id": "2018-firstround-55",
      "tournament_id": "2018-ncaa-mens",
      "team1_id": "Michigan",
      "team2_id": "Montana",
      "tipoff_time": "2018-03-15T00:00:00",
      "sort_order": 55,
      "team1_score": 61,
      "team2_score": 47,
      "next_game_id": "2018-secondround-60",
      "next_game_slot": 2,
      "is_final": true,
      "created": "2025-04-07T08:08:58.431633",
      "updated": "2025-04-07T08:08:58.431633"
    },
    {
      "id": "2018-firstround-56",
      "tournament_id": "2018-ncaa-mens",
      "team1_id": "Texas A&M",
      "team2_id": "Providence",
      "tipoff_time": "2018-03-16T00:00:00",
      "sort_order": 56,
      "team1_score": 73,
      "team2_score": 69,
      "next_game_id": "2018-secondround-61",
      "next_game_slot": 1,
      "is_final": true,
      "created": "2025-04-07T08:08:58.431678",
      "updated": "2025-04-07T08:08:58.431678"
    },
    {
      "id": "2018-firstround-57",
      "tournament_id": "2018-ncaa-mens",
      "team1_id": "UNC",
      "team2_id": "Lipscomb",
      "tipoff_time": "2018-03-16T00:00:00",
      "sort_order": 57,
      "team1_score": 84,
      "team2_score": 66,
      "next_game_id": "2018-secondround-61",
      "next_game_slot": 2,
      "is_final": true,
      "created": "2025-04-07T08:08:58.431723",
      "updated": "2025-04-07T08:08:58.431724"
    },
    {
      "id": "2018-secondround-58",
      "tournament_id": "2018-ncaa-mens",
      "team1_id": "Xavier",
      "team2_id": "Florida State",
      "tipoff_time": "2018-03-18T00:00:00",
      "sort_order": 58,
      "team1_score": 70,
      "team2_score": 75,
      "next_game_id": "2018-sweet16-62",
      "next_game_slot": 1,
      "is_final": true,
      "created": "2025-04-07T08:08:58.431784",
      "updated": "2025-04-07T08:08:58.431785"
    },
    {
      "id": "2018-secondround-59",
      "tournament_id": "2018-ncaa-mens",
      "team1_id": "Ohio State",
      "team2_id": "Gonzaga",
      "tipoff_time": "2018-03-17T00:00:00",
      "sort_order": 59,
      "team1_score": 84,
      "team2_score": 90,
      "next_game_id": "2018-sweet16-62",
      "next_game_slot": 2,
      "is_final": true,
      "created": "2025-04-07T08:08:58.431831",
      "updated": "2025-04-07T08:08:58.431832"
    },
    {
      "id": "2018-secondround-60",
      "tournament_id": "2018-ncaa-mens",
      "team1_id": "Houston",
      "team2_id": "Michigan",
      "tipoff_time": "2018-03-17T00:00:00",
      "sort_order": 60,
      "team1_score": 63,
      "team2_score": 64,
      "next_game_id": "2018-sweet16-63",
      "next_game_slot": 1,
      "is_final": true,
      "created": "2025-04-07T08:08:58.431878",
      "updated": "2025-04-07T08:08:58.431878"
    },
    {
      "id": "2018-secondround-61",
      "tournament_id": "2018-ncaa-mens",
      "team1_id": "Texas A&M",
      "team2_id": "UNC",
      "tipoff_time": "2018-03-18T00:00:00",
      "sort_order": 61,
      "team1_score": 86,
      "team2_score": 65,
      "next_game_id": "2018-sweet16-63",
      "next_game_slot": 2,
      "is_final": true,
      "created": "2025-04-07T08:08:58.431923",
      "updated": "2025-04-07T08:08:58.431924"
    },
    {
      "id": "2018-sweet16-62",
      "tournament_id": "2018-ncaa-mens",
      "team1_id": "Florida State",
      "team2_id": "Gonzaga",
      "tipoff_time": "2018-03-22T00:00:00",
      "sort_order": 62,
      "team1_score": 75,
      "team2_score": 60,
      "next_game_id": "2018-eliteeight-64",
      "next_game_slot": 1,
      "is_final": true,
      "created": "2025-04-07T08:08:58.431977",
      "updated": "2025-04-07T08:08:58.431977"
    },
    {
      "id": "2018-sweet16-63",
      "tournament_id": "2018-ncaa-mens",
      "team1_id": "Michigan",
      "team2_id": "Texas A&M",
      "tipoff_time": "2018-03-22T00:00:00",
      "sort_order": 63,
      "team1_score": 99,
      "team2_score": 72,
      "next_game_id": "2018-eliteeight-64",
      "next_game_slot": 2,
      "is_final": true,
      "created": "2025-04-07T08:08:58.432022",
      "updated": "2025-04-07T08:08:58.432022"
    },
    {
      "id": "2018-eliteeight-64",
      "tournament_id": "2018-ncaa-mens",
      "team1_id": "Florida State",
      "team2_id": "Michigan",
      "tipoff_time": "2018-03-24T00:00:00",
      "sort_order": 64,
      "team1_score": 54,
      "team2_score": 58,
      "next_game_id": "2018-finalfour-66",
      "next_game_slot": 2,
      "is_final": true,
      "created": "2025-04-07T08:08:58.432078",
      "updated": "2025-04-07T08:08:58.432078"
    },
    {
      "id": "2018-finalfour-65",
      "tournament_id": "2018-ncaa-mens",
      "team1_id": "Villanova",
      "team2_id": "Kansas",
      "tipoff_time": "2018-03-31T00:00:00",
      "sort_order": 65,
      "team1_score": 95,
      "team2_score": 79,
      "next_game_id": "2018-championship-67",
      "next_game_slot": 1,
      "is_final": true,
      "created": "2025-04-07T08:08:58.432309",
      "updated": "2025-04-07T08:08:58.432310"
    },
    {
      "id": "2018-finalfour-66",
      "tournament_id": "2018-ncaa-mens",
      "team1_id": "Loyola (IL)",
      "team2_id": "Michigan",
      "tipoff_time": "2018-03-31T00:00:00",
      "sort_order": 66,
      "team1_score": 57,
      "team2_score": 69,
      "next_game_id": "2018-championship-67",
      "next_game_slot": 2,
      "is_final": true,
      "created": "2025-04-07T08:08:58.432355",
      "updated": "2025-04-07T08:08:58.432356"
    },
    {
      "id": "2018-championship-67",
      "tournament_id": "2018-ncaa-mens",
      "team1_id": "Villanova",
      "team2_id": "Michigan",
      "tipoff_time": "2018-04-02T00:00:00",
      "sort_order": 67,
      "team1_score": 79,
      "team2_score": 62,
      "next_game_id": "",
      "next_game_slot": 1,
      "is_final": true,
      "created": "2025-04-07T08:08:58.432411",
      "updated": "2025-04-07T08:08:58.432411"
    }
  ]
}