{
  "id": "2021-ncaa-mens",
  "name": "NCAA Division I Men's Basketball Tournament",
  "rounds": 7,
  "games": [
    {
      "id": "2021-firstround-1",
      "tournament_id": "2021-ncaa-mens",
      "team1_id": "Michigan",
      "team2_id": "Texas Southern",
      "tipoff_time": "2021-03-20T00:00:00",
      "sort_order": 1,
      "team1_score": 82,
      "team2_score": 66,
      "next_game_id": "",
      "next_game_slot": 1,
      "is_final": true,
      "created": "2025-04-07T07:02:03.088189",
      "updated": "2025-04-07T07:02:03.088191"
    },
    {
      "id": "2021-firstround-2",
      "tournament_id": "2021-ncaa-mens",
      "team1_id": "LSU",
      "team2_id": "St. Bonaventure",
      "tipoff_time": "2021-03-20T00:00:00",
      "sort_order": 2,
      "team1_score": 76,
      "team2_score": 61,
      "next_game_id": "",
      "next_game_slot": 1,
      "is_final": true,
      "created": "2025-04-07T07:02:03.088249",
      "updated": "2025-04-07T07:02:03.088249"
    },
    {
      "id": "2021-firstround-3",
      "tournament_id": "2021-ncaa-mens",
      "team1_id": "Colorado",
      "team2_id": "Georgetown",
      "tipoff_time": "2021-03-20T00:00:00",
      "sort_order": 3,
      "team1_score": 96,
      "team2_score": 73,
      "next_game_id": "",
      "next_game_slot": 1,
      "is_final": true,
      "created": "2025-04-07T07:02:03.088299",
      "updated": "2025-04-07T07:02:03.088300"
    },
    {
      "id": "2021-firstround-4",
      "tournament_id": "2021-ncaa-mens",
      "team1_id": "Florida State",
      "team2_id": "UNC Greensboro",
      "tipoff_time": "2021-03-20T00:00:00",
      "sort_order": 4,
      "team1_score": 64,
      "team2_score": 54,
      "next_game_id": "",
      "next_game_slot": 1,
      "is_final": true,
      "created": "2025-04-07T07:02:03.088348",
      "updated": "2025-04-07T07:02:03.088349"
    },
    {
      "id": "2021-firstround-5",
      "tournament_id": "2021-ncaa-mens",
      "team1_id": "BYU",
      "team2_id": "UCLA",
      "tipoff_time": "2021-03-20T00:00:00",
      "sort_order": 5,
      "team1_score": 62,
      "team2_score": 73,
      "next_game_id": "",
      "next_game_slot": 1,
      "is_final": true,
      "created": "2025-04-07T07:02:03.088396",
      "updated": "2025-04-07T07:02:03.088396"
    },
    {
      "id": "2021-firstround-6",
      "tournament_id": "2021-ncaa-mens",
      "team1_id": "Texas",
      "team2_id": "Abilene Christian",
      "tipoff_time": "2021-03-20T00:00:00",
      "sort_order": 6,
      "team1_score": 52,
      "team2_score": 53,
      "next_game_id": "",
      "next_game_slot": 1,
      "is_final": true,
      "created": "2025-04-07T07:02:03.088443",
      "updated": "2025-04-07T07:02:03.088444"
    },
    {
      "id": "2021-firstround-7",
      "tournament_id": "2021-ncaa-mens",
      "team1_id": "UConn",
      "team2_id": "Maryland",
      "tipoff_time": "2021-03-20T00:00:00",
      "sort_order": 7,
      "team1_score": 54,
      "team2_score": 63,
      "next_game_id": "",
      "next_game_slot": 1,
      "is_final": true,
      "created": "2025-04-07T07:02:03.088492",
      "updated": "2025-04-07T07:02:03.088493"
    },
    {
      "id": "2021-firstround-8",
      "tournament_id": "2021-ncaa-mens",
      "team1_id": "Alabama",
      "team2_id": "Iona",
      "tipoff_time": "2021-03-20T00:00:00",
      "sort_order": 8,
      "team1_score": 68,
      "team2_score": 55,
      "next_game_id": "",
      "next_game_slot": 1,
      "is_final": true,
      "created": "2025-04-07T07:02:03.088541",
      "updated": "2025-04-07T07:02:03.088542"
    },
    {
      "id": "2021-secondround-9",
      "tournament_id": "2021-ncaa-mens",
      "team1_id": "Michigan",
      "team2_id": "LSU",
      "tipoff_time": "2021-03-22T00:00:00",
      "sort_order": 9,
      "team1_score": 86,
      "team2_score": 78,
      "next_game_id": "",
      "next_game_slot": 1,
      "is_final": true,
      "created": "2025-04-07T07:02:03.088602",
      "updated": "2025-04-07T07:02:03.088603"
    },
    {
      "id": "2021-secondround-10",
      "tournament_id": "2021-ncaa-mens",
      "team1_id": "Colorado",
      "team2_id": "Florida State",
      "tipoff_time": "2021-03-22T00:00:00",
      "sort_order": 10,
      "team1_score": 53,
      "team2_score": 71,
      "next_game_id": "",
      "next_game_slot": 1,
      "is_final": true,
      "created": "2025-04-07T07:02:03.088652",
      "updated": "2025-04-07T07:02:03.088652"
    },
    {
      "id": "2021-secondround-11",
      "tournament_id": "2021-ncaa-mens",
      "team1_id": "UCLA",
      "team2_id": "Abilene Christian",
      "tipoff_time": "2021-03-22T00:00:00",
      "sort_order": 11,
      "team1_score": 67,
      "team2_score": 47,
      "next_game_id": "",
      "next_game_slot": 1,
      "is_final": true,
      "created": "2025-04-07T07:02:03.088699",
      "updated": "2025-04-07T07:02:03.088700"
    },
    {
      "id": "2021-secondround-12",
      "tournament_id": "2021-ncaa-mens",
      "team1_id": "Maryland",
      "team2_id": "Alabama",
      "tipoff_time": "2021-03-22T00:00:00",
      "sort_order": 12,
      "team1_score": 77,
      "team2_score": 96,
      "next_game_id": "",
      "next_game_slot": 1,
      "is_final": true,
      "created": "2025-04-07T07:02:03.088747",
      "updated": "2025-04-07T07:02:03.088748"
    },
    {
      "id": "2021-sweet16-13",
      "tournament_id": "2021-ncaa-mens",
      "team1_id": "Michigan",
      "team2_id": "Florida State",
      "tipoff_time": "2021-03-28T00:00:00",
      "sort_order": 13,
      "team1_score": 76,
      "team2_score": 58,
      "next_game_id": "",
      "next_game_slot": 1,
      "is_final": true,
      "created": "2025-04-07T07:02:03.088804",
      "updated": "2025-04-07T07:02:03.088805"
    },
    {
      "id": "2021-sweet16-14",
      "tournament_id": "2021-ncaa-mens",
      "team1_id": "UCLA",
      "team2_id": "Alabama",
      "tipoff_time": "2021-03-28T00:00:00",
      "sort_order": 14,
      "team1_score": 88,
      "team2_score": 78,
      "next_game_id": "",
      "next_game_slot": 1,
      "is_final": true,
      "created": "2025-04-07T07:02:03.088853",
      "updated": "2025-04-07T07:02:03.088854"
    },
    {
      "id": "2021-eliteeight-15",
      "tournament_id": "2021-ncaa-mens",
      "team1_id": "Michigan",
      "team2_id": "UCLA",
      "tipoff_time": "2021-03-30T00:00:00",
      "sort_order": 15,
      "team1_score": 49,
      "team2_score": 51,
      "next_game_id": "",
      "next_game_slot": 1,
      "is_final": true,
      "created": "2025-04-07T07:02:03.088908",
      "updated": "2025-04-07T07:02:03.088908"
    },
    {
      "id": "2021-firstround-16",
      "tournament_id": "2021-ncaa-mens",
      "team1_id": "Illinois",
      "team2_id": "Drexel",
      "tipoff_time": "2021-03-19T00:00:00",
      "sort_order": 16,
      "team1_score": 78,
      "team2_score": 49,
      "next_game_id": "",
      "next_game_slot": 1,
      "is_final": true,
      "created": "2025-04-07T07:02:03.089670",
      "updated": "2025-04-07T07:02:03.089671"
    },
    {
      "id": "2021-firstround-17",
      "tournament_id": "2021-ncaa-mens",
      "team1_id": "Loyola (IL)",
      "team2_id": "Georgia Tech",
      "tipoff_time": "2021-03-19T00:00:00",
      "sort_order": 17,
      "team1_score": 71,
      "team2_score": 60,
      "next_game_id": "",
      "next_game_slot": 1,
      "is_final": true,
      "created": "2025-04-07T07:02:03.089721",
      "updated": "2025-04-07T07:02:03.089722"
    },
    {
      "id": "2021-firstround-18",
      "tournament_id": "2021-ncaa-mens",
      "team1_id": "Tennessee",
      "team2_id": "Oregon State",
      "tipoff_time": "2021-03-19T00:00:00",
      "sort_order": 18,
      "team1_score": 56,
      "team2_score": 70,
      "next_game_id": "",
      "next_game_slot": 1,
      "is_final": true,
      "created": "2025-04-07T07:02:03.089769",
      "updated": "2025-04-07T07:02:03.089770"
    },
    {
      "id": "2021-firstround-19",
      "tournament_id": "2021-ncaa-mens",
      "team1_id": "Oklahoma State",
      "team2_id": "Liberty",
      "tipoff_time": "2021-03-19T00:00:00",
      "sort_order": 19,
      "team1_score": 69,
      "team2_score": 60,
      "next_game_id": "",
      "next_game_slot": 1,
      "is_final": true,
      "created": "2025-04-07T07:02:03.089819",
      "updated": "2025-04-07T07:02:03.089819"
    },
    {
      "id": "2021-firstround-20",
      "tournament_id": "2021-ncaa-mens",
      "team1_id": "San Diego State",
      "team2_id": "Syracuse",
      "tipoff_time": "2021-03-19T00:00:00",
      "sort_order": 20,
      "team1_score": 62,
      "team2_score": 78,
      "next_game_id": "",
      "next_game_slot": 1,
      "is_final": true,
      "created": "2025-04-07T07:02:03.089880",
      "updated": "2025-04-07T07:02:03.089881"
    },
    {
      "id": "2021-firstround-21",
      "tournament_id": "2021-ncaa-mens",
      "team1_id": "West Virginia",
      "team2_id": "Morehead State",
      "tipoff_time": "2021-03-19T00:00:00",
      "sort_order": 21,
      "team1_score": 84,
      "team2_score": 67,
      "next_game_id": "",
      "next_game_slot": 1,
      "is_final": true,
      "created": "2025-04-07T07:02:03.089931",
      "updated": "2025-04-07T07:02:03.089932"
    },
    {
      "id": "2021-firstround-22",
      "tournament_id": "2021-ncaa-mens",
      "team1_id": "Clemson",
      "team2_id": "Rutgers",
      "tipoff_time": "2021-03-19T00:00:00",
      "sort_order": 22,
      "team1_score": 56,
      "team2_score": 60,
      "next_game_id": "",
      "next_game_slot": 1,
      "is_final": true,
      "created": "2025-04-07T07:02:03.089979",
      "updated": "2025-04-07T07:02:03.089979"
    },
    {
      "id": "2021-firstround-23",
      "tournament_id": "2021-ncaa-mens",
      "team1_id": "Houston",
      "team2_id": "Cleveland State",
      "tipoff_time": "2021-03-19T00:00:00",
      "sort_order": 23,
      "team1_score": 87,
      "team2_score": 56,
      "next_game_id": "",
      "next_game_slot": 1,
      "is_final": true,
      "created": "2025-04-07T07:02:03.090029",
      "updated": "2025-04-07T07:02:03.090029"
    },
    {
      "id": "2021-secondround-24",
      "tournament_id": "2021-ncaa-mens",
      "team1_id": "Illinois",
      "team2_id": "Loyola (IL)",
      "tipoff_time": "2021-03-21T00:00:00",
      "sort_order": 24,
      "team1_score": 58,
      "team2_score": 71,
      "next_game_id": "",
      "next_game_slot": 1,
      "is_final": true,
      "created": "2025-04-07T07:02:03.090089",
      "updated": "2025-04-07T07:02:03.090090"
    },
    {
      "id": "2021-secondround-25",
      "tournament_id": "2021-ncaa-mens",
      "team1_id": "Oregon State",
      "team2_id": "Oklahoma State",
      "tipoff_time": "2021-03-21T00:00:00",
      "sort_order": 25,
      "team1_score": 80,
      "team2_score": 70,
      "next_game_id": "",
      "next_game_slot": 1,
      "is_final": true,
      "created": "2025-04-07T07:02:03.090136",
      "updated": "2025-04-07T07:02:03.090137"
    },
    {
      "id": "2021-secondround-26",
      "tournament_id": "2021-ncaa-mens",
      "team1_id": "Syracuse",
      "team2_id": "West Virginia",
      "tipoff_time": "2021-03-21T00:00:00",
      "sort_order": 26,
      "team1_score": 75,
      "team2_score": 72,
      "next_game_id": "",
      "next_game_slot": 1,
      "is_final": true,
      "created": "2025-04-07T07:02:03.090182",
      "updated": "2025-04-07T07:02:03.090183"
    },
    {
      "id": "2021-secondround-27",
      "tournament_id": "2021-ncaa-mens",
      "team1_id": "Rutgers",
      "team2_id": "Houston",
      "tipoff_time": "2021-03-21T00:00:00",
      "sort_order": 27,
      "team1_score": 60,
      "team2_score": 63,
      "next_game_id": "",
      "next_game_slot": 1,
      "is_final": true,
      "created": "2025-04-07T07:02:03.090229",
      "updated": "2025-04-07T07:02:03.090229"
    },
    {
      "id": "2021-sweet16-28",
      "tournament_id": "2021-ncaa-mens",
      "team1_id": "Loyola (IL)",
      "team2_id": "Oregon State",
      "tipoff_time": "2021-03-27T00:00:00",
      "sort_order": 28,
      "team1_score": 58,
      "team2_score": 65,
      "next_game_id": "",
      "next_game_slot": 1,
      "is_final": true,
      "created": "2025-04-07T07:02:03.090284",
      "updated": "2025-04-07T07:02:03.090284"
    },
    {
      "id": "2021-sweet16-29",
      "tournament_id": "2021-ncaa-mens",
      "team1_id": "Syracuse",
      "team2_id": "Houston",
      "tipoff_time": "2021-03-27T00:00:00",
      "sort_order": 29,
      "team1_score": 46,
      "team2_score": 62,
      "next_game_id": "",
      "next_game_slot": 1,
      "is_final": true,
      "created": "2025-04-07T07:02:03.090330",
      "updated": "2025-04-07T07:02:03.090330"
    },
    {
      "id": "2021-eliteeight-30",
      "tournament_id": "2021-ncaa-mens",
      "team1_id": "Oregon State",
      "team2_id": "Houston",
      "tipoff_time": "2021-03-29T00:00:00",
      "sort_order": 30,
      "team1_score": 61,
      "team2_score": 67,
      "next_game_id": "",
      "next_game_slot": 1,
      "is_final": true,
      "created": "2025-04-07T07:02:03.090385",
      "updated": "2025-04-07T07:02:03.090385"
    },
    {
      "id": "2021-firstround-31",
      "tournament_id": "2021-ncaa-mens",
      "team1_id": "Baylor",
      "team2_id": "Hartford",
      "tipoff_time": "2021-03-19T00:00:00",
      "sort_order": 31,
      "team1_score": 79,
      "team2_score": 55,
      "next_game_id": "",
      "next_game_slot": 1,
      "is_final": true,
      "created": "2025-04-07T07:02:03.091095",
      "updated": "2025-04-07T07:02:03.091095"
    },
    {
      "id": "2021-firstround-32",
      "tournament_id": "2021-ncaa-mens",
      "team1_id": "UNC",
      "team2_id": "Wisconsin",
      "tipoff_time": "2021-03-19T00:00:00",
      "sort_order": 32,
      "team1_score": 62,
      "team2_score": 85,
      "next_game_id": "",
      "next_game_slot": 1,
      "is_final": true,
      "created": "2025-04-07T07:02:03.091141",
      "updated": "2025-04-07T07:02:03.091142"
    },
    {
      "id": "2021-firstround-33",
      "tournament_id": "2021-ncaa-mens",
      "team1_id": "Villanova",
      "team2_id": "Winthrop",
      "tipoff_time": "2021-03-19T00:00:00",
      "sort_order": 33,
      "team1_score": 73,
      "team2_score": 63,
      "next_game_id": "",
      "next_game_slot": 1,
      "is_final": true,
      "created": "2025-04-07T07:02:03.091188",
      "updated": "2025-04-07T07:02:03.091188"
    },
    {
      "id": "2021-firstround-34",
      "tournament_id": "2021-ncaa-mens",
      "team1_id": "Purdue",
      "team2_id": "North Texas",
      "tipoff_time": "2021-03-19T00:00:00",
      "sort_order": 34,
      "team1_score": 69,
      "team2_score": 78,
      "next_game_id": "",
      "next_game_slot": 1,
      "is_final": true,
      "created": "2025-04-07T07:02:03.091234",
      "updated": "2025-04-07T07:02:03.091234"
    },
    {
      "id": "2021-firstround-35",
      "tournament_id": "2021-ncaa-mens",
      "team1_id": "Texas Tech",
      "team2_id": "Utah State",
      "tipoff_time": "2021-03-19T00:00:00",
      "sort_order": 35,
      "team1_score": 65,
      "team2_score": 53,
      "next_game_id": "",
      "next_game_slot": 1,
      "is_final": true,
      "created": "2025-04-07T07:02:03.091280",
      "updated": "2025-04-07T07:02:03.091281"
    },
    {
      "id": "2021-firstround-36",
      "tournament_id": "2021-ncaa-mens",
      "team1_id": "Arkansas",
      "team2_id": "Colgate",
      "tipoff_time": "2021-03-19T00:00:00",
      "sort_order": 36,
      "team1_score": 85,
      "team2_score": 68,
      "next_game_id": "",
      "next_game_slot": 1,
      "is_final": true,
      "created": "2025-04-07T07:02:03.091326",
      "updated": "2025-04-07T07:02:03.091326"
    },
    {
      "id": "2021-firstround-37",
      "tournament_id": "2021-ncaa-mens",
      "team1_id": "Florida",
      "team2_id": "Virginia Tech",
      "tipoff_time": "2021-03-19T00:00:00",
      "sort_order": 37,
      "team1_score": 75,
      "team2_score": 70,
      "next_game_id": "",
      "next_game_slot": 1,
      "is_final": true,
      "created": "2025-04-07T07:02:03.091371",
      "updated": "2025-04-07T07:02:03.091372"
    },
    {
      "id": "2021-firstround-38",
      "tournament_id": "2021-ncaa-mens",
      "team1_id": "Ohio State",
      "team2_id": "Oral Roberts",
      "tipoff_time": "2021-03-19T00:00:00",
      "sort_order": 38,
      "team1_score": 72,
      "team2_score": 75,
      "next_game_id": "",
      "next_game_slot": 1,
      "is_final": true,
      "created": "2025-04-07T07:02:03.091420",
      "updated": "2025-04-07T07:02:03.091420"
    },
    {
      "id": "2021-secondround-39",
      "tournament_id": "2021-ncaa-mens",
      "team1_id": "Baylor",
      "team2_id": "Wisconsin",
      "tipoff_time": "2021-03-21T00:00:00",
      "sort_order": 39,
      "team1_score": 76,
      "team2_score": 63,
      "next_game_id": "",
      "next_game_slot": 1,
      "is_final": true,
      "created": "2025-04-07T07:02:03.091479",
      "updated": "2025-04-07T07:02:03.091479"
    },
    {
      "id": "2021-secondround-40",
      "tournament_id": "2021-ncaa-mens",
      "team1_id": "Villanova",
      "team2_id": "North Texas",
      "tipoff_time": "2021-03-21T00:00:00",
      "sort_order": 40,
      "team1_score": 84,
      "team2_score": 61,
      "next_game_id": "",
      "next_game_slot": 1,
      "is_final": true,
      "created": "2025-04-07T07:02:03.091620",
      "updated": "2025-04-07T07:02:03.091622"
    },
    {
      "id": "2021-secondround-41",
      "tournament_id": "2021-ncaa-mens",
      "team1_id": "Texas Tech",
      "team2_id": "Arkansas",
      "tipoff_time": "2021-03-21T00:00:00",
      "sort_order": 41,
      "team1_score": 66,
      "team2_score": 68,
      "next_game_id": "",
      "next_game_slot": 1,
      "is_final": true,
      "created": "2025-04-07T07:02:03.091697",
      "updated": "2025-04-07T07:02:03.091698"
    },
    {
      "id": "2021-secondround-42",
      "tournament_id": "2021-ncaa-mens",
      "team1_id": "Florida",
      "team2_id": "Oral Roberts",
      "tipoff_time": "2021-03-21T00:00:00",
      "sort_order": 42,
      "team1_score": 78,
      "team2_score": 81,
      "next_game_id": "",
      "next_game_slot": 1,
      "is_final": true,
      "created": "2025-04-07T07:02:03.091749",
      "updated": "2025-04-07T07:02:03.091750"
    },
    {
      "id": "2021-sweet16-43",
      "tournament_id": "2021-ncaa-mens",
      "team1_id": "Baylor",
      "team2_id": "Villanova",
      "tipoff_time": "2021-03-27T00:00:00",
      "sort_order": 43,
      "team1_score": 62,
      "team2_score": 51,
      "next_game_id": "",
      "next_game_slot": 1,
      "is_final": true,
      "created": "2025-04-07T07:02:03.091822",
      "updated": "2025-04-07T07:02:03.091823"
    },
    {
      "id": "2021-sweet16-44",
      "tournament_id": "2021-ncaa-mens",
      "team1_id": "Arkansas",
      "team2_id": "Oral Roberts",
      "tipoff_time": "2021-03-27T00:00:00",
      "sort_order": 44,
      "team1_score": 72,
      "team2_score": 70,
      "next_game_id": "",
      "next_game_slot": 1,
      "is_final": true,
      "created": "2025-04-07T07:02:03.091871",
      "updated": "2025-04-07T07:02:03.091872"
    },
    {
      "id": "2021-eliteeight-45",
      "tournament_id": "2021-ncaa-mens",
      "team1_id": "Baylor",
      "team2_id": "Arkansas",
      "tipoff_time": "2021-03-29T00:00:00",
      "sort_order": 45,
      "team1_score": 81,
      "team2_score": 72,
      "next_game_id": "",
      "next_game_slot": 1,
      "is_final": true,
      "created": "2025-04-07T07:02:03.091930",
      "updated": "2025-04-07T07:02:03.091930"
    },
    {
      "id": "2021-firstround-46",
      "tournament_id": "2021-ncaa-mens",
      "team1_id": "Gonzaga",
      "team2_id": "Norfolk State",
      "tipoff_time": "2021-03-20T00:00:00",
      "sort_order": 46,
      "team1_score": 98,
      "team2_score": 55,
      "next_game_id": "",
      "next_game_slot": 1,
      "is_final": true,
      "created": "2025-04-07T07:02:03.092581",
      "updated": "2025-04-07T07:02:03.092581"
    },
    {
      "id": "2021-firstround-47",
      "tournament_id": "2021-ncaa-mens",
      "team1_id": "Oklahoma",
      "team2_id": "Missouri",
      "tipoff_time": "2021-03-20T00:00:00",
      "sort_order": 47,
      "team1_score": 72,
      "team2_score": 68,
      "next_game_id": "",
      "next_game_slot": 1,
      "is_final": true,
      "created": "2025-04-07T07:02:03.092626",
      "updated": "2025-04-07T07:02:03.092627"
    },
    {
      "id": "2021-firstround-48",
      "tournament_id": "2021-ncaa-mens",
      "team1_id": "Creighton",
      "team2_id": "UCSB",
      "tipoff_time": "2021-03-20T00:00:00",
      "sort_order": 48,
      "team1_score": 63,
      "team2_score": 62,
      "next_game_id": "",
      "next_game_slot": 1,
      "is_final": true,
      "created": "2025-04-07T07:02:03.092671",
      "updated": "2025-04-07T07:02:03.092672"
    },
    {
      "id": "2021-firstround-49",
      "tournament_id": "2021-ncaa-mens",
      "team1_id": "Virginia",
      "team2_id": "Ohio",
      "tipoff_time": "2021-03-20T00:00:00",
      "sort_order": 49,
      "team1_score": 58,
      "team2_score": 62,
      "next_game_id": "",
      "next_game_slot": 1,
      "is_final": true,
      "created": "2025-04-07T07:02:03.092715",
      "updated": "2025-04-07T07:02:03.092716"
    },
    {
      "id": "2021-firstround-50",
      "tournament_id": "2021-ncaa-mens",
      "team1_id": "USC",
      "team2_id": "Drake",
      "tipoff_time": "2021-03-20T00:00:00",
      "sort_order": 50,
      "team1_score": 72,
      "team2_score": 56,
      "next_game_id": "",
      "next_game_slot": 1,
      "is_final": true,
      "created": "2025-04-07T07:02:03.092759",
      "updated": "2025-04-07T07:02:03.092760"
    },
    {
      "id": "2021-firstround-51",
      "tournament_id": "2021-ncaa-mens",
      "team1_id": "Kansas",
      "team2_id": "Eastern Washington",
      "tipoff_time": "2021-03-20T00:00:00",
      "sort_order": 51,
      "team1_score": 93,
      "team2_score": 84,
      "next_game_id": "",
      "next_game_slot": 1,
      "is_final": true,
      "created": "2025-04-07T07:02:03.092803",
      "updated": "2025-04-07T07:02:03.092804"
    },
    {
      "id": "2021-firstround-52",
      "tournament_id": "2021-ncaa-mens",
      "team1_id": "Iowa",
      "team2_id": "Grand Canyon",
      "tipoff_time": "2021-03-20T00:00:00",
      "sort_order": 52,
      "team1_score": 86,
      "team2_score": 74,
      "next_game_id": "",
      "next_game_slot": 1,
      "is_final": true,
      "created": "2025-04-07T07:02:03.092874",
      "updated": "2025-04-07T07:02:03.092874"
    },
    {
      "id": "2021-secondround-53",
      "tournament_id": "2021-ncaa-mens",
      "team1_id": "Gonzaga",
      "team2_id": "Oklahoma",
      "tipoff_time": "2021-03-22T00:00:00",
      "sort_order": 53,
      "team1_score": 87,
      "team2_score": 71,
      "next_game_id": "",
      "next_game_slot": 1,
      "is_final": true,
      "created": "2025-04-07T07:02:03.092929",
      "updated": "2025-04-07T07:02:03.092930"
    },
    {
      "id": "2021-secondround-54",
      "tournament_id": "2021-ncaa-mens",
      "team1_id": "Creighton",
      "team2_id": "Ohio",
      "tipoff_time": "2021-03-22T00:00:00",
      "sort_order": 54,
      "team1_score": 72,
      "team2_score": 58,
      "next_game_id": "",
      "next_game_slot": 1,
      "is_final": true,
      "created": "2025-04-07T07:02:03.092974",
      "updated": "2025-04-07T07:02:03.092974"
    },
    {
      "id": "2021-secondround-55",
      "tournament_id": "2021-ncaa-mens",
      "team1_id": "USC",
      "team2_id": "Kansas",
      "tipoff_time": "2021-03-22T00:00:00",
      "sort_order": 55,
      "team1_score": 85,
      "team2_score": 51,
      "next_game_id": "",
      "next_game_slot": 1,
      "is_final": true,
      "created": "2025-04-07T07:02:03.093018",
      "updated": "2025-04-07T07:02:03.093018"
    },
    {
      "id": "2021-secondround-56",
      "tournament_id": "2021-ncaa-mens",
      "team1_id": "Oregon",
      "team2_id": "Iowa",
      "tipoff_time": "2021-03-22T00:00:00",
      "sort_order": 56,
      "team1_score": 95,
      "team2_score": 80,
      "next_game_id": "",
      "next_game_slot": 1,
      "is_final": true,
      "created": "2025-04-07T07:02:03.093061",
      "updated": "2025-04-07T07:02:03.093062"
    },
    {
      "id": "2021-sweet16-57",
      "tournament_id": "2021-ncaa-mens",
      "team1_id": "Gonzaga",
      "team2_id": "Creighton",
      "tipoff_time": "2021-03-28T00:00:00",
      "sort_order": 57,
      "team1_score": 83,
      "team2_score": 65,
      "next_game_id": "",
      "next_game_slot": 1,
      "is_final": true,
      "created": "2025-04-07T07:02:03.093116",
      "updated": "2025-04-07T07:02:03.093117"
    },
    {
      "id": "2021-sweet16-58",
      "tournament_id": "2021-ncaa-mens",
      "team1_id": "USC",
      "team2_id": "Oregon",
      "tipoff_time": "2021-03-28T00:00:00",
      "sort_order": 58,
      "team1_score": 82,
      "team2_score": 68,
      "next_game_id": "",
      "next_game_slot": 1,
      "is_final": true,
      "created": "2025-04-07T07:02:03.093160",
      "updated": "2025-04-07T07:02:03.093161"
    },
    {
      "id": "2021-eliteeight-59",
      "tournament_id": "2021-ncaa-mens",
      "team1_id": "Gonzaga",
      "team2_id": "USC",
      "tipoff_time": "2021-03-30T00:00:00",
      "sort_order": 59,
      "team1_score": 85,
      "team2_score": 66,
      "next_game_id": "",
      "next_game_slot": 1,
      "is_final": true,
      "created": "2025-04-07T07:02:03.093214",
      "updated": "2025-04-07T07:02:03.093215"
    },
    {
      "id": "2021-finalfour-60",
      "tournament_id": "2021-ncaa-mens",
      "team1_id": "Baylor",
      "team2_id": "Houston",
      "tipoff_time": "2021-04-03T00:00:00",
      "sort_order": 60,
      "team1_score": 78,
      "team2_score": 59,
      "next_game_id": "",
      "next_game_slot": 1,
      "is_final": true,
      "created": "2025-04-07T07:02:03.093437",
      "updated": "2025-04-07T07:02:03.093438"
    },
    {
      "id": "2021-finalfour-61",
      "tournament_id": "2021-ncaa-mens",
      "team1_id": "Gonzaga",
      "team2_id": "UCLA",
      "tipoff_time": "2021-04-03T00:00:00",
      "sort_order": 61,
      "team1_score": 93,
      "team2_score": 90,
      "next_game_id": "",
      "next_game_slot": 1,
      "is_final": true,
      "created": "2025-04-07T07:02:03.093483",
      "updated": "2025-04-07T07:02:03.093483"
    },
    {
      "id": "2021-championship-62",
      "tournament_id": "2021-ncaa-mens",
      "team1_id": "Baylor",
      "team2_id": "Gonzaga",
      "tipoff_time": "2021-04-05T00:00:00",
      "sort_order": 62,
      "team1_score": 86,
      "team2_score": 70,
      "next_game_id": "",
      "next_game_slot": 1,
      "is_final": true,
      "created": "2025-04-07T07:02:03.093536",
      "updated": "2025-04-07T07:02:03.093537"
    }
  ]
}